setup.py
workbook/__init__.py
workbook.egg-info/PKG-INFO
workbook.egg-info/SOURCES.txt
workbook.egg-info/dependency_links.txt
workbook.egg-info/requires.txt
workbook.egg-info/top_level.txt