Metadata-Version: 1.0
Name: workbook
Version: 1.1
Summary: App that creates xls reports, or tables, from simple lists
Home-page: https://github.com/daleobrien/workbook
Author: Dale O'Brien
Author-email: dale@do.id.au
License: UNKNOWN
Platform: UNKNOWN
Classifier: Development Status :: 5 - Production/Stable
Classifier: Natural Language :: English
Classifier: Programming Language :: Python
Classifier: Programming Language :: Python :: 2.6
Classifier: Programming Language :: Python :: 2.7
